src/__init__.py
src/listener.py
src/notifier.py
src/payload_types.py
tests/__init__.py
pg_listen-0.0.1b1.dist-info/LICENSE
pg_listen-0.0.1b1.dist-info/METADATA
pg_listen-0.0.1b1.dist-info/WHEEL
pg_listen-0.0.1b1.dist-info/top_level.txt
pg_listen-0.0.1b1.dist-info/RECORD
