Metadata-Version: 2.1
Name: pg-listen
Version: 0.0.1b1
Summary: Testing installation of Package
Home-page: https://github.com/llownall/pg-notify
Author: llownall
Author-email: toxa1996@inbox.ru
License: MIT
Platform: UNKNOWN
License-File: LICENSE
Requires-Dist: psycopg2 (>=2.7)
